{"is_source_file": false, "format": "", "description": "", "external_files": [], "external_methods": [], "published": [], "classes": [], "methods": [], "calls": [], "search-terms": [], "state": 2, "file_id": 4, "knowledge_revision": 26, "git_revision": "fdfbde6c8ad782aca88905c7aebb0fe4d638a167", "hash": "12e6b98db03097f87daa6bafd98f6237", "format-version": 4, "code-base-name": "user_projects_frontend", "filename": "user_projects_frontend/src/index.css", "revision_history": [{"26": "fdfbde6c8ad782aca88905c7aebb0fe4d638a167"}]}